{
  "discovered": {
    "/signin": {
      "items": {
        "info": [
          {
            "text": "Sign in",
            "details": "Sign in",
            "type": null,
            "locator": "h1"
          },
          {
            "text": "Username",
            "details": "Username",
            "type": null,
            "locator": "legend.PrivateNotchedOutline-legendNotched-83 > span"
          },
          {
            "text": "Password",
            "details": "Password",
            "type": null,
            "locator": "div[data-test=\"signin-password\"] > div > fieldset > legend > span"
          },
          {
            "text": "",
            "details": "",
            "type": null,
            "locator": "span[aria-disabled=\"false\"]"
          },
          {
            "text": "",
            "details": "",
            "type": null,
            "locator": "span.MuiIconButton-label"
          },
          {
            "text": "",
            "details": "",
            "type": null,
            "locator": "span[aria-disabled=\"false\"] > span:nth-of-type(2)"
          },
          {
            "text": "Remember me",
            "details": "Remember me",
            "type": null,
            "locator": "span.MuiTypography-root"
          },
          {
            "text": "Sign In",
            "details": "Sign In",
            "type": null,
            "locator": "span.MuiButton-label"
          },
          {
            "text": "",
            "details": "",
            "type": null,
            "locator": "button > span:nth-of-type(2)"
          },
          {
            "text": "Built by",
            "details": "Built by",
            "type": null,
            "locator": "p"
          }
        ],
        "input": [
          {
            "text": "",
            "details": null,
            "type": "text",
            "locator": "input#username"
          },
          {
            "text": "",
            "details": null,
            "type": "password",
            "locator": "input#password"
          },
          {
            "text": "",
            "details": null,
            "type": "checkbox",
            "locator": "input[name=\"remember\"]"
          }
        ],
        "actions": [
          {
            "text": "Sign In",
            "locator": "button"
          },
          {
            "text": "Don't have an account? Sign Up",
            "locator": "a[data-test=\"signup\"]"
          },
          {
            "text": "",
            "locator": "a[target=\"_blank\"]"
          }
        ],
        "iterable": []
      }
    },
    "/": {
      "items": {
        "info": [
          {
            "text": "",
            "details": "",
            "type": null,
            "locator": "h1"
          },
          {
            "text": "Devon B",
            "details": "Devon B",
            "type": null,
            "locator": "h6[data-test=\"sidenav-user-full-name\"]"
          },
          {
            "text": "@Jessyca.Kuhic",
            "details": "@Jessyca.Kuhic",
            "type": null,
            "locator": "h6[data-test=\"sidenav-username\"]"
          },
          {
            "text": "$623.69",
            "details": "$623.69",
            "type": null,
            "locator": "h6[data-test=\"sidenav-user-balance\"]"
          },
          {
            "text": "Account Balance",
            "details": "Account Balance",
            "type": null,
            "locator": "div.MuiDrawer-paper > div:nth-of-type(2) > div:nth-of-type(1) > h6:nth-of-type(2)"
          },
          {
            "text": "",
            "details": "",
            "type": null,
            "locator": "button > span:nth-of-type(1)"
          },
          {
            "text": "",
            "details": "",
            "type": null,
            "locator": "button > span:nth-of-type(2)"
          },
          {
            "text": " New",
            "details": "New",
            "type": null,
            "locator": "span.MuiButton-label"
          },
          {
            "text": "",
            "details": "",
            "type": null,
            "locator": "a[data-test=\"nav-top-new-transaction\"] > span:nth-of-type(2)"
          },
          {
            "text": "8",
            "details": "8",
            "type": null,
            "locator": "a[data-test=\"nav-top-notifications-link\"] > span:nth-of-type(1)"
          },
          {
            "text": "8",
            "details": "8",
            "type": null,
            "locator": "span[data-test=\"nav-top-notifications-count\"]"
          },
          {
            "text": "8",
            "details": "8",
            "type": null,
            "locator": "span.makeStyles-customBadge-28"
          },
          {
            "text": "",
            "details": "",
            "type": null,
            "locator": "a[data-test=\"nav-top-notifications-link\"] > span:nth-of-type(2)"
          },
          {
            "text": "Everyone",
            "details": "Everyone",
            "type": null,
            "locator": "a[aria-selected=\"true\"] > span:nth-of-type(1)"
          },
          {
            "text": "",
            "details": "",
            "type": null,
            "locator": "a[aria-selected=\"true\"] > span:nth-of-type(2)"
          },
          {
            "text": "Friends",
            "details": "Friends",
            "type": null,
            "locator": "a[data-test=\"nav-contacts-tab\"] > span:nth-of-type(1)"
          },
          {
            "text": "",
            "details": "",
            "type": null,
            "locator": "a[data-test=\"nav-contacts-tab\"] > span:nth-of-type(2)"
          },
          {
            "text": "Mine",
            "details": "Mine",
            "type": null,
            "locator": "a[data-test=\"nav-personal-tab\"] > span:nth-of-type(1)"
          },
          {
            "text": "",
            "details": "",
            "type": null,
            "locator": "a[data-test=\"nav-personal-tab\"] > span:nth-of-type(2)"
          },
          {
            "text": "",
            "details": "",
            "type": null,
            "locator": "span.PrivateTabIndicator-root-29"
          },
          {
            "text": "Home",
            "details": "Home",
            "type": null,
            "locator": "a[data-test=\"sidenav-home\"] > div:nth-of-type(2) > span"
          },
          {
            "text": "",
            "details": "",
            "type": null,
            "locator": "a[data-test=\"sidenav-home\"] > span"
          },
          {
            "text": "My Account",
            "details": "My Account",
            "type": null,
            "locator": "a[data-test=\"sidenav-user-settings\"] > div:nth-of-type(2) > span"
          },
          {
            "text": "",
            "details": "",
            "type": null,
            "locator": "a[data-test=\"sidenav-user-settings\"] > span"
          },
          {
            "text": "Bank Accounts",
            "details": "Bank Accounts",
            "type": null,
            "locator": "a[data-test=\"sidenav-bankaccounts\"] > div:nth-of-type(2) > span"
          },
          {
            "text": "",
            "details": "",
            "type": null,
            "locator": "a[data-test=\"sidenav-bankaccounts\"] > span"
          },
          {
            "text": "Notifications",
            "details": "Notifications",
            "type": null,
            "locator": "a[data-test=\"sidenav-notifications\"] > div:nth-of-type(2) > span"
          },
          {
            "text": "",
            "details": "",
            "type": null,
            "locator": "a[data-test=\"sidenav-notifications\"] > span"
          },
          {
            "text": "Logout",
            "details": "Logout",
            "type": null,
            "locator": "div[aria-disabled=\"false\"] > div:nth-of-type(2) > span"
          },
          {
            "text": "",
            "details": "",
            "type": null,
            "locator": "div[aria-disabled=\"false\"] > span"
          },
          {
            "text": "Date: ALL",
            "details": "Date: ALL",
            "type": null,
            "locator": "div[data-test=\"transaction-list-filter-date-range-button\"] > span:nth-of-type(1)"
          },
          {
            "text": "",
            "details": "",
            "type": null,
            "locator": "div[data-test=\"transaction-list-filter-date-range-button\"] > span:nth-of-type(2)"
          },
          {
            "text": "Amount: $0 - $1,000",
            "details": "Amount: $0 - $1,000",
            "type": null,
            "locator": "div[data-test=\"transaction-list-filter-amount-range-button\"] > span:nth-of-type(1)"
          },
          {
            "text": "",
            "details": "",
            "type": null,
            "locator": "div[data-test=\"transaction-list-filter-amount-range-button\"] > span:nth-of-type(2)"
          },
          {
            "text": "",
            "details": "",
            "type": null,
            "locator": "li[data-test=\"transaction-item-kI6EuGgcV\"] > div > div > div:nth-of-type(1) > div > span"
          },
          {
            "text": "",
            "details": "",
            "type": null,
            "locator": "li[data-test=\"transaction-item-kI6EuGgcV\"] > div > div > div:nth-of-type(1) > div > span > span"
          },
          {
            "text": "Devon Becker",
            "details": "Devon Becker",
            "type": null,
            "locator": "span[data-test=\"transaction-sender-kI6EuGgcV\"]"
          },
          {
            "text": " paid ",
            "details": "paid",
            "type": null,
            "locator": "span[data-test=\"transaction-action-kI6EuGgcV\"]"
          },
          {
            "text": "Edgar Johns",
            "details": "Edgar Johns",
            "type": null,
            "locator": "span[data-test=\"transaction-receiver-kI6EuGgcV\"]"
          },
          {
            "text": "-$13.00",
            "details": "-$13.00",
            "type": null,
            "locator": "span[data-test=\"transaction-amount-kI6EuGgcV\"]"
          },
          {
            "text": "",
            "details": "",
            "type": null,
            "locator": "li[data-test=\"transaction-item-E9PfY8ScJ\"] > div > div > div:nth-of-type(1) > div > span"
          },
          {
            "text": "",
            "details": "",
            "type": null,
            "locator": "li[data-test=\"transaction-item-E9PfY8ScJ\"] > div > div > div:nth-of-type(1) > div > span > span"
          },
          {
            "text": "Devon Becker",
            "details": "Devon Becker",
            "type": null,
            "locator": "span[data-test=\"transaction-sender-E9PfY8ScJ\"]"
          },
          {
            "text": " paid ",
            "details": "paid",
            "type": null,
            "locator": "span[data-test=\"transaction-action-E9PfY8ScJ\"]"
          },
          {
            "text": "Edgar Johns",
            "details": "Edgar Johns",
            "type": null,
            "locator": "span[data-test=\"transaction-receiver-E9PfY8ScJ\"]"
          },
          {
            "text": "-$13.00",
            "details": "-$13.00",
            "type": null,
            "locator": "span[data-test=\"transaction-amount-E9PfY8ScJ\"]"
          },
          {
            "text": "",
            "details": "",
            "type": null,
            "locator": "li[data-test=\"transaction-item-Gk9JamYBE\"] > div > div > div:nth-of-type(1) > div > span"
          },
          {
            "text": "",
            "details": "",
            "type": null,
            "locator": "li[data-test=\"transaction-item-Gk9JamYBE\"] > div > div > div:nth-of-type(1) > div > span > span"
          },
          {
            "text": "Devon Becker",
            "details": "Devon Becker",
            "type": null,
            "locator": "span[data-test=\"transaction-sender-Gk9JamYBE\"]"
          },
          {
            "text": " paid ",
            "details": "paid",
            "type": null,
            "locator": "span[data-test=\"transaction-action-Gk9JamYBE\"]"
          },
          {
            "text": "Edgar Johns",
            "details": "Edgar Johns",
            "type": null,
            "locator": "span[data-test=\"transaction-receiver-Gk9JamYBE\"]"
          },
          {
            "text": "-$13.00",
            "details": "-$13.00",
            "type": null,
            "locator": "span[data-test=\"transaction-amount-Gk9JamYBE\"]"
          },
          {
            "text": "",
            "details": "",
            "type": null,
            "locator": "li[data-test=\"transaction-item-55v-Eqnhk\"] > div > div > div:nth-of-type(1) > div > span"
          },
          {
            "text": "",
            "details": "",
            "type": null,
            "locator": "li[data-test=\"transaction-item-55v-Eqnhk\"] > div > div > div:nth-of-type(1) > div > span > span"
          },
          {
            "text": "Devon Becker",
            "details": "Devon Becker",
            "type": null,
            "locator": "span[data-test=\"transaction-sender-55v-Eqnhk\"]"
          },
          {
            "text": " paid ",
            "details": "paid",
            "type": null,
            "locator": "span[data-test=\"transaction-action-55v-Eqnhk\"]"
          },
          {
            "text": "Edgar Johns",
            "details": "Edgar Johns",
            "type": null,
            "locator": "span[data-test=\"transaction-receiver-55v-Eqnhk\"]"
          },
          {
            "text": "-$13.00",
            "details": "-$13.00",
            "type": null,
            "locator": "span[data-test=\"transaction-amount-55v-Eqnhk\"]"
          },
          {
            "text": "",
            "details": "",
            "type": null,
            "locator": "li[data-test=\"transaction-item-Z46U8Foq8\"] > div > div > div:nth-of-type(1) > div > span"
          },
          {
            "text": "",
            "details": "",
            "type": null,
            "locator": "li[data-test=\"transaction-item-Z46U8Foq8\"] > div > div > div:nth-of-type(1) > div > span > span"
          },
          {
            "text": "Devon Becker",
            "details": "Devon Becker",
            "type": null,
            "locator": "span[data-test=\"transaction-sender-Z46U8Foq8\"]"
          },
          {
            "text": " paid ",
            "details": "paid",
            "type": null,
            "locator": "span[data-test=\"transaction-action-Z46U8Foq8\"]"
          },
          {
            "text": "Edgar Johns",
            "details": "Edgar Johns",
            "type": null,
            "locator": "span[data-test=\"transaction-receiver-Z46U8Foq8\"]"
          },
          {
            "text": "-$13.00",
            "details": "-$13.00",
            "type": null,
            "locator": "span[data-test=\"transaction-amount-Z46U8Foq8\"]"
          },
          {
            "text": "",
            "details": "",
            "type": null,
            "locator": "li[data-test=\"transaction-item-mEYl_ZSc5Qqe\"] > div > div > div:nth-of-type(1) > div > span"
          },
          {
            "text": "",
            "details": "",
            "type": null,
            "locator": "li[data-test=\"transaction-item-mEYl_ZSc5Qqe\"] > div > div > div:nth-of-type(1) > div > span > span"
          },
          {
            "text": "Kaylin Homenick",
            "details": "Kaylin Homenick",
            "type": null,
            "locator": "span[data-test=\"transaction-sender-mEYl_ZSc5Qqe\"]"
          },
          {
            "text": " requested ",
            "details": "requested",
            "type": null,
            "locator": "span[data-test=\"transaction-action-mEYl_ZSc5Qqe\"]"
          },
          {
            "text": "Devon Becker",
            "details": "Devon Becker",
            "type": null,
            "locator": "span[data-test=\"transaction-receiver-mEYl_ZSc5Qqe\"]"
          },
          {
            "text": "+$290.01",
            "details": "+$290.01",
            "type": null,
            "locator": "span[data-test=\"transaction-amount-mEYl_ZSc5Qqe\"]"
          },
          {
            "text": "",
            "details": "",
            "type": null,
            "locator": "li[data-test=\"transaction-item-Ke0eaLoOG8Dg\"] > div > div > div:nth-of-type(1) > div > span"
          },
          {
            "text": "",
            "details": "",
            "type": null,
            "locator": "li[data-test=\"transaction-item-Ke0eaLoOG8Dg\"] > div > div > div:nth-of-type(1) > div > span > span"
          },
          {
            "text": "Kaylin Homenick",
            "details": "Kaylin Homenick",
            "type": null,
            "locator": "span[data-test=\"transaction-sender-Ke0eaLoOG8Dg\"]"
          },
          {
            "text": " charged ",
            "details": "charged",
            "type": null,
            "locator": "span[data-test=\"transaction-action-Ke0eaLoOG8Dg\"]"
          },
          {
            "text": "Devon Becker",
            "details": "Devon Becker",
            "type": null,
            "locator": "span[data-test=\"transaction-receiver-Ke0eaLoOG8Dg\"]"
          },
          {
            "text": "+$483.79",
            "details": "+$483.79",
            "type": null,
            "locator": "span[data-test=\"transaction-amount-Ke0eaLoOG8Dg\"]"
          },
          {
            "text": "",
            "details": "",
            "type": null,
            "locator": "li[data-test=\"transaction-item-8YnLpItFazLO\"] > div > div > div:nth-of-type(1) > div > span"
          },
          {
            "text": "",
            "details": "",
            "type": null,
            "locator": "li[data-test=\"transaction-item-8YnLpItFazLO\"] > div > div > div:nth-of-type(1) > div > span > span"
          },
          {
            "text": "Devon Becker",
            "details": "Devon Becker",
            "type": null,
            "locator": "span[data-test=\"transaction-sender-8YnLpItFazLO\"]"
          },
          {
            "text": " paid ",
            "details": "paid",
            "type": null,
            "locator": "span[data-test=\"transaction-action-8YnLpItFazLO\"]"
          },
          {
            "text": "Kaylin Homenick",
            "details": "Kaylin Homenick",
            "type": null,
            "locator": "span[data-test=\"transaction-receiver-8YnLpItFazLO\"]"
          },
          {
            "text": "-$414.57",
            "details": "-$414.57",
            "type": null,
            "locator": "span[data-test=\"transaction-amount-8YnLpItFazLO\"]"
          },
          {
            "text": "",
            "details": "",
            "type": null,
            "locator": "li[data-test=\"transaction-item-WfxoygTKhJHU\"] > div > div > div:nth-of-type(1) > div > span"
          },
          {
            "text": "",
            "details": "",
            "type": null,
            "locator": "li[data-test=\"transaction-item-WfxoygTKhJHU\"] > div > div > div:nth-of-type(1) > div > span > span"
          },
          {
            "text": "Kaylin Homenick",
            "details": "Kaylin Homenick",
            "type": null,
            "locator": "span[data-test=\"transaction-sender-WfxoygTKhJHU\"]"
          },
          {
            "text": " requested ",
            "details": "requested",
            "type": null,
            "locator": "span[data-test=\"transaction-action-WfxoygTKhJHU\"]"
          },
          {
            "text": "Devon Becker",
            "details": "Devon Becker",
            "type": null,
            "locator": "span[data-test=\"transaction-receiver-WfxoygTKhJHU\"]"
          },
          {
            "text": "+$438.50",
            "details": "+$438.50",
            "type": null,
            "locator": "span[data-test=\"transaction-amount-WfxoygTKhJHU\"]"
          },
          {
            "text": "",
            "details": "",
            "type": null,
            "locator": "li[data-test=\"transaction-item-NMrYdkrY_18W\"] > div > div > div:nth-of-type(1) > div > span"
          },
          {
            "text": "",
            "details": "",
            "type": null,
            "locator": "li[data-test=\"transaction-item-NMrYdkrY_18W\"] > div > div > div:nth-of-type(1) > div > span > span"
          },
          {
            "text": "Kaylin Homenick",
            "details": "Kaylin Homenick",
            "type": null,
            "locator": "span[data-test=\"transaction-sender-NMrYdkrY_18W\"]"
          },
          {
            "text": " charged ",
            "details": "charged",
            "type": null,
            "locator": "span[data-test=\"transaction-action-NMrYdkrY_18W\"]"
          },
          {
            "text": "Devon Becker",
            "details": "Devon Becker",
            "type": null,
            "locator": "span[data-test=\"transaction-receiver-NMrYdkrY_18W\"]"
          },
          {
            "text": "+$220.54",
            "details": "+$220.54",
            "type": null,
            "locator": "span[data-test=\"transaction-amount-NMrYdkrY_18W\"]"
          },
          {
            "text": "Devon Becker paid Edgar Johns",
            "details": "Devon Becker paid Edgar Johns",
            "type": null,
            "locator": "li[data-test=\"transaction-item-kI6EuGgcV\"] > div > div > div:nth-of-type(2) > div:nth-of-type(1) > div > p:nth-of-type(1)"
          },
          {
            "text": "Payment-542608",
            "details": "Payment-542608",
            "type": null,
            "locator": "li[data-test=\"transaction-item-kI6EuGgcV\"] > div > div > div:nth-of-type(2) > div:nth-of-type(1) > div > p:nth-of-type(2)"
          },
          {
            "text": "0",
            "details": "0",
            "type": null,
            "locator": "li[data-test=\"transaction-item-kI6EuGgcV\"] > div > div > div:nth-of-type(2) > div:nth-of-type(1) > div > div > div:nth-of-type(2) > p"
          },
          {
            "text": "0",
            "details": "0",
            "type": null,
            "locator": "li[data-test=\"transaction-item-kI6EuGgcV\"] > div > div > div:nth-of-type(2) > div:nth-of-type(1) > div > div > div:nth-of-type(4) > p"
          },
          {
            "text": "Devon Becker paid Edgar Johns",
            "details": "Devon Becker paid Edgar Johns",
            "type": null,
            "locator": "li[data-test=\"transaction-item-E9PfY8ScJ\"] > div > div > div:nth-of-type(2) > div:nth-of-type(1) > div > p:nth-of-type(1)"
          },
          {
            "text": "Payment-970537",
            "details": "Payment-970537",
            "type": null,
            "locator": "li[data-test=\"transaction-item-E9PfY8ScJ\"] > div > div > div:nth-of-type(2) > div:nth-of-type(1) > div > p:nth-of-type(2)"
          },
          {
            "text": "0",
            "details": "0",
            "type": null,
            "locator": "li[data-test=\"transaction-item-E9PfY8ScJ\"] > div > div > div:nth-of-type(2) > div:nth-of-type(1) > div > div > div:nth-of-type(2) > p"
          },
          {
            "text": "0",
            "details": "0",
            "type": null,
            "locator": "li[data-test=\"transaction-item-E9PfY8ScJ\"] > div > div > div:nth-of-type(2) > div:nth-of-type(1) > div > div > div:nth-of-type(4) > p"
          },
          {
            "text": "Devon Becker paid Edgar Johns",
            "details": "Devon Becker paid Edgar Johns",
            "type": null,
            "locator": "li[data-test=\"transaction-item-Gk9JamYBE\"] > div > div > div:nth-of-type(2) > div:nth-of-type(1) > div > p:nth-of-type(1)"
          },
          {
            "text": "Payment-238177",
            "details": "Payment-238177",
            "type": null,
            "locator": "li[data-test=\"transaction-item-Gk9JamYBE\"] > div > div > div:nth-of-type(2) > div:nth-of-type(1) > div > p:nth-of-type(2)"
          },
          {
            "text": "0",
            "details": "0",
            "type": null,
            "locator": "li[data-test=\"transaction-item-Gk9JamYBE\"] > div > div > div:nth-of-type(2) > div:nth-of-type(1) > div > div > div:nth-of-type(2) > p"
          },
          {
            "text": "0",
            "details": "0",
            "type": null,
            "locator": "li[data-test=\"transaction-item-Gk9JamYBE\"] > div > div > div:nth-of-type(2) > div:nth-of-type(1) > div > div > div:nth-of-type(4) > p"
          },
          {
            "text": "Devon Becker paid Edgar Johns",
            "details": "Devon Becker paid Edgar Johns",
            "type": null,
            "locator": "li[data-test=\"transaction-item-55v-Eqnhk\"] > div > div > div:nth-of-type(2) > div:nth-of-type(1) > div > p:nth-of-type(1)"
          },
          {
            "text": "Payment-950983",
            "details": "Payment-950983",
            "type": null,
            "locator": "li[data-test=\"transaction-item-55v-Eqnhk\"] > div > div > div:nth-of-type(2) > div:nth-of-type(1) > div > p:nth-of-type(2)"
          },
          {
            "text": "0",
            "details": "0",
            "type": null,
            "locator": "li[data-test=\"transaction-item-55v-Eqnhk\"] > div > div > div:nth-of-type(2) > div:nth-of-type(1) > div > div > div:nth-of-type(2) > p"
          },
          {
            "text": "0",
            "details": "0",
            "type": null,
            "locator": "li[data-test=\"transaction-item-55v-Eqnhk\"] > div > div > div:nth-of-type(2) > div:nth-of-type(1) > div > div > div:nth-of-type(4) > p"
          },
          {
            "text": "Devon Becker paid Edgar Johns",
            "details": "Devon Becker paid Edgar Johns",
            "type": null,
            "locator": "li[data-test=\"transaction-item-Z46U8Foq8\"] > div > div > div:nth-of-type(2) > div:nth-of-type(1) > div > p:nth-of-type(1)"
          },
          {
            "text": "Payment-572350",
            "details": "Payment-572350",
            "type": null,
            "locator": "li[data-test=\"transaction-item-Z46U8Foq8\"] > div > div > div:nth-of-type(2) > div:nth-of-type(1) > div > p:nth-of-type(2)"
          },
          {
            "text": "0",
            "details": "0",
            "type": null,
            "locator": "li[data-test=\"transaction-item-Z46U8Foq8\"] > div > div > div:nth-of-type(2) > div:nth-of-type(1) > div > div > div:nth-of-type(2) > p"
          },
          {
            "text": "0",
            "details": "0",
            "type": null,
            "locator": "li[data-test=\"transaction-item-Z46U8Foq8\"] > div > div > div:nth-of-type(2) > div:nth-of-type(1) > div > div > div:nth-of-type(4) > p"
          },
          {
            "text": "Kaylin Homenick requested Devon Becker",
            "details": "Kaylin Homenick requested Devon Becker",
            "type": null,
            "locator": "li[data-test=\"transaction-item-mEYl_ZSc5Qqe\"] > div > div > div:nth-of-type(2) > div:nth-of-type(1) > div > p:nth-of-type(1)"
          },
          {
            "text": "Request: tsHF6_D5oQ to bDjUb4ir5O",
            "details": "Request: tsHF6_D5oQ to bDjUb4ir5O",
            "type": null,
            "locator": "li[data-test=\"transaction-item-mEYl_ZSc5Qqe\"] > div > div > div:nth-of-type(2) > div:nth-of-type(1) > div > p:nth-of-type(2)"
          },
          {
            "text": "0",
            "details": "0",
            "type": null,
            "locator": "li[data-test=\"transaction-item-mEYl_ZSc5Qqe\"] > div > div > div:nth-of-type(2) > div:nth-of-type(1) > div > div > div:nth-of-type(2) > p"
          },
          {
            "text": "0",
            "details": "0",
            "type": null,
            "locator": "li[data-test=\"transaction-item-mEYl_ZSc5Qqe\"] > div > div > div:nth-of-type(2) > div:nth-of-type(1) > div > div > div:nth-of-type(4) > p"
          },
          {
            "text": "Kaylin Homenick charged Devon Becker",
            "details": "Kaylin Homenick charged Devon Becker",
            "type": null,
            "locator": "li[data-test=\"transaction-item-Ke0eaLoOG8Dg\"] > div > div > div:nth-of-type(2) > div:nth-of-type(1) > div > p:nth-of-type(1)"
          },
          {
            "text": "Request: tsHF6_D5oQ to bDjUb4ir5O",
            "details": "Request: tsHF6_D5oQ to bDjUb4ir5O",
            "type": null,
            "locator": "li[data-test=\"transaction-item-Ke0eaLoOG8Dg\"] > div > div > div:nth-of-type(2) > div:nth-of-type(1) > div > p:nth-of-type(2)"
          },
          {
            "text": "0",
            "details": "0",
            "type": null,
            "locator": "li[data-test=\"transaction-item-Ke0eaLoOG8Dg\"] > div > div > div:nth-of-type(2) > div:nth-of-type(1) > div > div > div:nth-of-type(2) > p"
          },
          {
            "text": "0",
            "details": "0",
            "type": null,
            "locator": "li[data-test=\"transaction-item-Ke0eaLoOG8Dg\"] > div > div > div:nth-of-type(2) > div:nth-of-type(1) > div > div > div:nth-of-type(4) > p"
          },
          {
            "text": "Devon Becker paid Kaylin Homenick",
            "details": "Devon Becker paid Kaylin Homenick",
            "type": null,
            "locator": "li[data-test=\"transaction-item-8YnLpItFazLO\"] > div > div > div:nth-of-type(2) > div:nth-of-type(1) > div > p:nth-of-type(1)"
          },
          {
            "text": "Payment: tsHF6_D5oQ to bDjUb4ir5O",
            "details": "Payment: tsHF6_D5oQ to bDjUb4ir5O",
            "type": null,
            "locator": "li[data-test=\"transaction-item-8YnLpItFazLO\"] > div > div > div:nth-of-type(2) > div:nth-of-type(1) > div > p:nth-of-type(2)"
          },
          {
            "text": "0",
            "details": "0",
            "type": null,
            "locator": "li[data-test=\"transaction-item-8YnLpItFazLO\"] > div > div > div:nth-of-type(2) > div:nth-of-type(1) > div > div > div:nth-of-type(2) > p"
          },
          {
            "text": "0",
            "details": "0",
            "type": null,
            "locator": "li[data-test=\"transaction-item-8YnLpItFazLO\"] > div > div > div:nth-of-type(2) > div:nth-of-type(1) > div > div > div:nth-of-type(4) > p"
          },
          {
            "text": "Kaylin Homenick requested Devon Becker",
            "details": "Kaylin Homenick requested Devon Becker",
            "type": null,
            "locator": "li[data-test=\"transaction-item-WfxoygTKhJHU\"] > div > div > div:nth-of-type(2) > div:nth-of-type(1) > div > p:nth-of-type(1)"
          },
          {
            "text": "Request: tsHF6_D5oQ to bDjUb4ir5O",
            "details": "Request: tsHF6_D5oQ to bDjUb4ir5O",
            "type": null,
            "locator": "li[data-test=\"transaction-item-WfxoygTKhJHU\"] > div > div > div:nth-of-type(2) > div:nth-of-type(1) > div > p:nth-of-type(2)"
          },
          {
            "text": "0",
            "details": "0",
            "type": null,
            "locator": "li[data-test=\"transaction-item-WfxoygTKhJHU\"] > div > div > div:nth-of-type(2) > div:nth-of-type(1) > div > div > div:nth-of-type(2) > p"
          },
          {
            "text": "0",
            "details": "0",
            "type": null,
            "locator": "li[data-test=\"transaction-item-WfxoygTKhJHU\"] > div > div > div:nth-of-type(2) > div:nth-of-type(1) > div > div > div:nth-of-type(4) > p"
          },
          {
            "text": "Kaylin Homenick charged Devon Becker",
            "details": "Kaylin Homenick charged Devon Becker",
            "type": null,
            "locator": "li[data-test=\"transaction-item-NMrYdkrY_18W\"] > div > div > div:nth-of-type(2) > div:nth-of-type(1) > div > p:nth-of-type(1)"
          },
          {
            "text": "Request: tsHF6_D5oQ to bDjUb4ir5O",
            "details": "Request: tsHF6_D5oQ to bDjUb4ir5O",
            "type": null,
            "locator": "li[data-test=\"transaction-item-NMrYdkrY_18W\"] > div > div > div:nth-of-type(2) > div:nth-of-type(1) > div > p:nth-of-type(2)"
          },
          {
            "text": "0",
            "details": "0",
            "type": null,
            "locator": "li[data-test=\"transaction-item-NMrYdkrY_18W\"] > div > div > div:nth-of-type(2) > div:nth-of-type(1) > div > div > div:nth-of-type(2) > p"
          },
          {
            "text": "0",
            "details": "0",
            "type": null,
            "locator": "li[data-test=\"transaction-item-NMrYdkrY_18W\"] > div > div > div:nth-of-type(2) > div:nth-of-type(1) > div > div > div:nth-of-type(4) > p"
          },
          {
            "text": "Built by",
            "details": "Built by",
            "type": null,
            "locator": "p.MuiTypography-alignCenter"
          }
        ],
        "input": [],
        "actions": [
          {
            "text": "",
            "locator": "button"
          },
          {
            "text": "",
            "locator": "a.MuiTypography-root"
          },
          {
            "text": " New",
            "locator": "a[data-test=\"nav-top-new-transaction\"]"
          },
          {
            "text": "8",
            "locator": "a[data-test=\"nav-top-notifications-link\"]"
          },
          {
            "text": "Everyone",
            "locator": "a[aria-selected=\"true\"]"
          },
          {
            "text": "Friends",
            "locator": "a[data-test=\"nav-contacts-tab\"]"
          },
          {
            "text": "Mine",
            "locator": "a[data-test=\"nav-personal-tab\"]"
          },
          {
            "text": "Home",
            "locator": "a[data-test=\"sidenav-home\"]"
          },
          {
            "text": "My Account",
            "locator": "a[data-test=\"sidenav-user-settings\"]"
          },
          {
            "text": "Bank Accounts",
            "locator": "a[data-test=\"sidenav-bankaccounts\"]"
          },
          {
            "text": "Notifications",
            "locator": "a[data-test=\"sidenav-notifications\"]"
          },
          {
            "text": "",
            "locator": "a[target=\"_blank\"]"
          }
        ],
        "iterable": [
          {
            "locator": "ul, ol",
            "iteratorName": "List Iterator",
            "elements": []
          },
          {
            "locator": "[data-test='transaction-list'] > div > div > div",
            "identifier": ".MuiTypography-body2",
            "iteratorName": "Transaction Iterator",
            "elements": [
              {
                "text": "Payment-542608",
                "locator": "p.MuiTypography-body2"
              }
            ]
          }
        ]
      }
    },
    "/transaction/new": {
      "items": {
        "info": [
          {
            "text": "",
            "details": "",
            "type": null,
            "locator": "h1"
          },
          {
            "text": "Devon B",
            "details": "Devon B",
            "type": null,
            "locator": "h6[data-test=\"sidenav-user-full-name\"]"
          },
          {
            "text": "@Jessyca.Kuhic",
            "details": "@Jessyca.Kuhic",
            "type": null,
            "locator": "h6[data-test=\"sidenav-username\"]"
          },
          {
            "text": "$675.69",
            "details": "$675.69",
            "type": null,
            "locator": "h6[data-test=\"sidenav-user-balance\"]"
          },
          {
            "text": "Account Balance",
            "details": "Account Balance",
            "type": null,
            "locator": "div.MuiDrawer-paper > div:nth-of-type(2) > div:nth-of-type(1) > h6:nth-of-type(2)"
          },
          {
            "text": "Edgar Johns",
            "details": "Edgar Johns",
            "type": null,
            "locator": "div.MuiGrid-direction-xs-column > div:nth-of-type(2) > h2"
          },
          {
            "text": "Paid $13.00 for Payment-572350",
            "details": "Paid $13.00 for Payment-572350",
            "type": null,
            "locator": "div.MuiGrid-justify-content-xs-center > div > h2"
          },
          {
            "text": "",
            "details": "",
            "type": null,
            "locator": "button[data-test=\"sidenav-toggle\"] > span:nth-of-type(1)"
          },
          {
            "text": "",
            "details": "",
            "type": null,
            "locator": "button[data-test=\"sidenav-toggle\"] > span:nth-of-type(2)"
          },
          {
            "text": " New",
            "details": "New",
            "type": null,
            "locator": "a[data-test=\"nav-top-new-transaction\"] > span:nth-of-type(1)"
          },
          {
            "text": "",
            "details": "",
            "type": null,
            "locator": "a[data-test=\"nav-top-new-transaction\"] > span:nth-of-type(2)"
          },
          {
            "text": "8",
            "details": "8",
            "type": null,
            "locator": "a[data-test=\"nav-top-notifications-link\"] > span:nth-of-type(1)"
          },
          {
            "text": "8",
            "details": "8",
            "type": null,
            "locator": "span[data-test=\"nav-top-notifications-count\"]"
          },
          {
            "text": "8",
            "details": "8",
            "type": null,
            "locator": "span.MuiBadge-badge"
          },
          {
            "text": "",
            "details": "",
            "type": null,
            "locator": "a[data-test=\"nav-top-notifications-link\"] > span:nth-of-type(2)"
          },
          {
            "text": "Home",
            "details": "Home",
            "type": null,
            "locator": "a[data-test=\"sidenav-home\"] > div:nth-of-type(2) > span"
          },
          {
            "text": "",
            "details": "",
            "type": null,
            "locator": "a[data-test=\"sidenav-home\"] > span"
          },
          {
            "text": "My Account",
            "details": "My Account",
            "type": null,
            "locator": "a[data-test=\"sidenav-user-settings\"] > div:nth-of-type(2) > span"
          },
          {
            "text": "",
            "details": "",
            "type": null,
            "locator": "a[data-test=\"sidenav-user-settings\"] > span"
          },
          {
            "text": "Bank Accounts",
            "details": "Bank Accounts",
            "type": null,
            "locator": "a[data-test=\"sidenav-bankaccounts\"] > div:nth-of-type(2) > span"
          },
          {
            "text": "",
            "details": "",
            "type": null,
            "locator": "a[data-test=\"sidenav-bankaccounts\"] > span"
          },
          {
            "text": "Notifications",
            "details": "Notifications",
            "type": null,
            "locator": "a[data-test=\"sidenav-notifications\"] > div:nth-of-type(2) > span"
          },
          {
            "text": "",
            "details": "",
            "type": null,
            "locator": "a[data-test=\"sidenav-notifications\"] > span"
          },
          {
            "text": "Logout",
            "details": "Logout",
            "type": null,
            "locator": "div[tabindex=\"0\"] > div:nth-of-type(2) > span"
          },
          {
            "text": "",
            "details": "",
            "type": null,
            "locator": "div[tabindex=\"0\"] > span"
          },
          {
            "text": "Select Contact",
            "details": "Select Contact",
            "type": null,
            "locator": "div.MuiStepper-root > div:nth-of-type(1) > span"
          },
          {
            "text": "",
            "details": "",
            "type": null,
            "locator": "div.MuiStepper-root > div:nth-of-type(1) > span > span:nth-of-type(1)"
          },
          {
            "text": "Select Contact",
            "details": "Select Contact",
            "type": null,
            "locator": "div.MuiStepper-root > div:nth-of-type(1) > span > span:nth-of-type(2)"
          },
          {
            "text": "Select Contact",
            "details": "Select Contact",
            "type": null,
            "locator": "div.MuiStepper-root > div:nth-of-type(1) > span > span:nth-of-type(2) > span"
          },
          {
            "text": "",
            "details": "",
            "type": null,
            "locator": "div.MuiStepper-root > div:nth-of-type(2) > span"
          },
          {
            "text": "Payment",
            "details": "Payment",
            "type": null,
            "locator": "div.MuiStepper-root > div:nth-of-type(3) > span"
          },
          {
            "text": "",
            "details": "",
            "type": null,
            "locator": "div.MuiStepper-root > div:nth-of-type(3) > span > span:nth-of-type(1)"
          },
          {
            "text": "Payment",
            "details": "Payment",
            "type": null,
            "locator": "div.MuiStepper-root > div:nth-of-type(3) > span > span:nth-of-type(2)"
          },
          {
            "text": "Payment",
            "details": "Payment",
            "type": null,
            "locator": "div.MuiStepper-root > div:nth-of-type(3) > span > span:nth-of-type(2) > span"
          },
          {
            "text": "",
            "details": "",
            "type": null,
            "locator": "div.MuiStepper-root > div:nth-of-type(4) > span"
          },
          {
            "text": "Complete",
            "details": "Complete",
            "type": null,
            "locator": "div.MuiStepper-root > div:nth-of-type(5) > span"
          },
          {
            "text": "",
            "details": "",
            "type": null,
            "locator": "div.MuiStepper-root > div:nth-of-type(5) > span > span:nth-of-type(1)"
          },
          {
            "text": "Complete",
            "details": "Complete",
            "type": null,
            "locator": "div.MuiStepper-root > div:nth-of-type(5) > span > span:nth-of-type(2)"
          },
          {
            "text": "Complete",
            "details": "Complete",
            "type": null,
            "locator": "div.MuiStepper-root > div:nth-of-type(5) > span > span:nth-of-type(2) > span"
          },
          {
            "text": "Return To Transactions",
            "details": "Return To Transactions",
            "type": null,
            "locator": "a[data-test=\"new-transaction-return-to-transactions\"] > span:nth-of-type(1)"
          },
          {
            "text": "",
            "details": "",
            "type": null,
            "locator": "a[data-test=\"new-transaction-return-to-transactions\"] > span:nth-of-type(2)"
          },
          {
            "text": "Create Another Transaction",
            "details": "Create Another Transaction",
            "type": null,
            "locator": "button[data-test=\"new-transaction-create-another-transaction\"] > span:nth-of-type(1)"
          },
          {
            "text": "",
            "details": "",
            "type": null,
            "locator": "button[data-test=\"new-transaction-create-another-transaction\"] > span:nth-of-type(2)"
          },
          {
            "text": "Built by",
            "details": "Built by",
            "type": null,
            "locator": "p"
          }
        ],
        "input": [],
        "actions": [
          {
            "text": "",
            "locator": "button[data-test=\"sidenav-toggle\"]"
          },
          {
            "text": "",
            "locator": "a.MuiTypography-root"
          },
          {
            "text": " New",
            "locator": "a[data-test=\"nav-top-new-transaction\"]"
          },
          {
            "text": "8",
            "locator": "a[data-test=\"nav-top-notifications-link\"]"
          },
          {
            "text": "Home",
            "locator": "a[data-test=\"sidenav-home\"]"
          },
          {
            "text": "My Account",
            "locator": "a[data-test=\"sidenav-user-settings\"]"
          },
          {
            "text": "Bank Accounts",
            "locator": "a[data-test=\"sidenav-bankaccounts\"]"
          },
          {
            "text": "Notifications",
            "locator": "a[data-test=\"sidenav-notifications\"]"
          },
          {
            "text": "Return To Transactions",
            "locator": "a[data-test=\"new-transaction-return-to-transactions\"]"
          },
          {
            "text": "Create Another Transaction",
            "locator": "button[data-test=\"new-transaction-create-another-transaction\"]"
          },
          {
            "text": "",
            "locator": "a[target=\"_blank\"]"
          }
        ],
        "iterable": [
          {
            "locator": "ul, ol",
            "iteratorName": "List Iterator",
            "elements": []
          }
        ]
      }
    },
    "/transaction/krCl7-EnC": {
      "items": {
        "info": [
          {
            "text": "",
            "details": "",
            "type": null,
            "locator": "h1"
          },
          {
            "text": "Devon B",
            "details": "Devon B",
            "type": null,
            "locator": "h6[data-test=\"sidenav-user-full-name\"]"
          },
          {
            "text": "@Jessyca.Kuhic",
            "details": "@Jessyca.Kuhic",
            "type": null,
            "locator": "h6[data-test=\"sidenav-username\"]"
          },
          {
            "text": "$701.69",
            "details": "$701.69",
            "type": null,
            "locator": "h6[data-test=\"sidenav-user-balance\"]"
          },
          {
            "text": "Account Balance",
            "details": "Account Balance",
            "type": null,
            "locator": "div.MuiDrawer-paper > div:nth-of-type(2) > div:nth-of-type(1) > h6:nth-of-type(2)"
          },
          {
            "text": "Transaction Detail",
            "details": "Transaction Detail",
            "type": null,
            "locator": "h2"
          },
          {
            "text": "",
            "details": "",
            "type": null,
            "locator": "button[data-test=\"sidenav-toggle\"] > span:nth-of-type(1)"
          },
          {
            "text": "",
            "details": "",
            "type": null,
            "locator": "button[data-test=\"sidenav-toggle\"] > span:nth-of-type(2)"
          },
          {
            "text": " New",
            "details": "New",
            "type": null,
            "locator": "span.MuiButton-label"
          },
          {
            "text": "",
            "details": "",
            "type": null,
            "locator": "a[data-test=\"nav-top-new-transaction\"] > span:nth-of-type(2)"
          },
          {
            "text": "8",
            "details": "8",
            "type": null,
            "locator": "a[data-test=\"nav-top-notifications-link\"] > span:nth-of-type(1)"
          },
          {
            "text": "8",
            "details": "8",
            "type": null,
            "locator": "span[data-test=\"nav-top-notifications-count\"]"
          },
          {
            "text": "8",
            "details": "8",
            "type": null,
            "locator": "span.MuiBadge-badge"
          },
          {
            "text": "",
            "details": "",
            "type": null,
            "locator": "a[data-test=\"nav-top-notifications-link\"] > span:nth-of-type(2)"
          },
          {
            "text": "Home",
            "details": "Home",
            "type": null,
            "locator": "a[data-test=\"sidenav-home\"] > div:nth-of-type(2) > span"
          },
          {
            "text": "",
            "details": "",
            "type": null,
            "locator": "a[data-test=\"sidenav-home\"] > span"
          },
          {
            "text": "My Account",
            "details": "My Account",
            "type": null,
            "locator": "a[data-test=\"sidenav-user-settings\"] > div:nth-of-type(2) > span"
          },
          {
            "text": "",
            "details": "",
            "type": null,
            "locator": "a[data-test=\"sidenav-user-settings\"] > span"
          },
          {
            "text": "Bank Accounts",
            "details": "Bank Accounts",
            "type": null,
            "locator": "a[data-test=\"sidenav-bankaccounts\"] > div:nth-of-type(2) > span"
          },
          {
            "text": "",
            "details": "",
            "type": null,
            "locator": "a[data-test=\"sidenav-bankaccounts\"] > span"
          },
          {
            "text": "Notifications",
            "details": "Notifications",
            "type": null,
            "locator": "a[data-test=\"sidenav-notifications\"] > div:nth-of-type(2) > span"
          },
          {
            "text": "",
            "details": "",
            "type": null,
            "locator": "a[data-test=\"sidenav-notifications\"] > span"
          },
          {
            "text": "Logout",
            "details": "Logout",
            "type": null,
            "locator": "div[tabindex=\"0\"] > div:nth-of-type(2) > span"
          },
          {
            "text": "",
            "details": "",
            "type": null,
            "locator": "div[tabindex=\"0\"] > span"
          },
          {
            "text": "Devon Becker",
            "details": "Devon Becker",
            "type": null,
            "locator": "span[data-test=\"transaction-sender-krCl7-EnC\"]"
          },
          {
            "text": " paid ",
            "details": "paid",
            "type": null,
            "locator": "span[data-test=\"transaction-action-krCl7-EnC\"]"
          },
          {
            "text": "Edgar Johns",
            "details": "Edgar Johns",
            "type": null,
            "locator": "span[data-test=\"transaction-receiver-krCl7-EnC\"]"
          },
          {
            "text": "-$13.00",
            "details": "-$13.00",
            "type": null,
            "locator": "span[data-test=\"transaction-amount-krCl7-EnC\"]"
          },
          {
            "text": "",
            "details": "",
            "type": null,
            "locator": "button[data-test=\"transaction-like-button-krCl7-EnC\"] > span:nth-of-type(1)"
          },
          {
            "text": "",
            "details": "",
            "type": null,
            "locator": "button[data-test=\"transaction-like-button-krCl7-EnC\"] > span:nth-of-type(2)"
          },
          {
            "text": "",
            "details": "",
            "type": null,
            "locator": "legend > span"
          },
          {
            "text": "Devon Becker paid Edgar Johns",
            "details": "Devon Becker paid Edgar Johns",
            "type": null,
            "locator": "p.makeStyles-title-117"
          },
          {
            "text": "Payment-539609",
            "details": "Payment-539609",
            "type": null,
            "locator": "p[data-test=\"transaction-description\"]"
          },
          {
            "text": "Built by",
            "details": "Built by",
            "type": null,
            "locator": "p.MuiTypography-alignCenter"
          }
        ],
        "input": [
          {
            "text": "",
            "details": "Write a comment...",
            "type": "text",
            "locator": "input"
          }
        ],
        "actions": [
          {
            "text": "",
            "locator": "button[data-test=\"sidenav-toggle\"]"
          },
          {
            "text": "",
            "locator": "a.MuiTypography-root"
          },
          {
            "text": " New",
            "locator": "a[data-test=\"nav-top-new-transaction\"]"
          },
          {
            "text": "8",
            "locator": "a[data-test=\"nav-top-notifications-link\"]"
          },
          {
            "text": "Home",
            "locator": "a[data-test=\"sidenav-home\"]"
          },
          {
            "text": "My Account",
            "locator": "a[data-test=\"sidenav-user-settings\"]"
          },
          {
            "text": "Bank Accounts",
            "locator": "a[data-test=\"sidenav-bankaccounts\"]"
          },
          {
            "text": "Notifications",
            "locator": "a[data-test=\"sidenav-notifications\"]"
          },
          {
            "text": "",
            "locator": "button[data-test=\"transaction-like-button-krCl7-EnC\"]"
          },
          {
            "text": "",
            "locator": "a[target=\"_blank\"]"
          }
        ],
        "iterable": [
          {
            "locator": "ul, ol",
            "iteratorName": "List Iterator",
            "elements": []
          }
        ]
      }
    },
    "/transaction/8bFo_NwEf": {
      "items": {
        "info": [
          {
            "text": "",
            "details": "",
            "type": null,
            "locator": "h1"
          },
          {
            "text": "Devon B",
            "details": "Devon B",
            "type": null,
            "locator": "h6[data-test=\"sidenav-user-full-name\"]"
          },
          {
            "text": "@Jessyca.Kuhic",
            "details": "@Jessyca.Kuhic",
            "type": null,
            "locator": "h6[data-test=\"sidenav-username\"]"
          },
          {
            "text": "$688.69",
            "details": "$688.69",
            "type": null,
            "locator": "h6[data-test=\"sidenav-user-balance\"]"
          },
          {
            "text": "Account Balance",
            "details": "Account Balance",
            "type": null,
            "locator": "div.MuiDrawer-paper > div:nth-of-type(2) > div:nth-of-type(1) > h6:nth-of-type(2)"
          },
          {
            "text": "Transaction Detail",
            "details": "Transaction Detail",
            "type": null,
            "locator": "h2"
          },
          {
            "text": "",
            "details": "",
            "type": null,
            "locator": "button[data-test=\"sidenav-toggle\"] > span:nth-of-type(1)"
          },
          {
            "text": "",
            "details": "",
            "type": null,
            "locator": "button[data-test=\"sidenav-toggle\"] > span:nth-of-type(2)"
          },
          {
            "text": " New",
            "details": "New",
            "type": null,
            "locator": "span.MuiButton-label"
          },
          {
            "text": "",
            "details": "",
            "type": null,
            "locator": "a[data-test=\"nav-top-new-transaction\"] > span:nth-of-type(2)"
          },
          {
            "text": "8",
            "details": "8",
            "type": null,
            "locator": "a[data-test=\"nav-top-notifications-link\"] > span:nth-of-type(1)"
          },
          {
            "text": "8",
            "details": "8",
            "type": null,
            "locator": "span[data-test=\"nav-top-notifications-count\"]"
          },
          {
            "text": "8",
            "details": "8",
            "type": null,
            "locator": "span.MuiBadge-badge"
          },
          {
            "text": "",
            "details": "",
            "type": null,
            "locator": "a[data-test=\"nav-top-notifications-link\"] > span:nth-of-type(2)"
          },
          {
            "text": "Home",
            "details": "Home",
            "type": null,
            "locator": "a[data-test=\"sidenav-home\"] > div:nth-of-type(2) > span"
          },
          {
            "text": "",
            "details": "",
            "type": null,
            "locator": "a[data-test=\"sidenav-home\"] > span"
          },
          {
            "text": "My Account",
            "details": "My Account",
            "type": null,
            "locator": "a[data-test=\"sidenav-user-settings\"] > div:nth-of-type(2) > span"
          },
          {
            "text": "",
            "details": "",
            "type": null,
            "locator": "a[data-test=\"sidenav-user-settings\"] > span"
          },
          {
            "text": "Bank Accounts",
            "details": "Bank Accounts",
            "type": null,
            "locator": "a[data-test=\"sidenav-bankaccounts\"] > div:nth-of-type(2) > span"
          },
          {
            "text": "",
            "details": "",
            "type": null,
            "locator": "a[data-test=\"sidenav-bankaccounts\"] > span"
          },
          {
            "text": "Notifications",
            "details": "Notifications",
            "type": null,
            "locator": "a[data-test=\"sidenav-notifications\"] > div:nth-of-type(2) > span"
          },
          {
            "text": "",
            "details": "",
            "type": null,
            "locator": "a[data-test=\"sidenav-notifications\"] > span"
          },
          {
            "text": "Logout",
            "details": "Logout",
            "type": null,
            "locator": "div[tabindex=\"0\"] > div:nth-of-type(2) > span"
          },
          {
            "text": "",
            "details": "",
            "type": null,
            "locator": "div[tabindex=\"0\"] > span"
          },
          {
            "text": "Devon Becker",
            "details": "Devon Becker",
            "type": null,
            "locator": "span[data-test=\"transaction-sender-8bFo_NwEf\"]"
          },
          {
            "text": " paid ",
            "details": "paid",
            "type": null,
            "locator": "span[data-test=\"transaction-action-8bFo_NwEf\"]"
          },
          {
            "text": "Edgar Johns",
            "details": "Edgar Johns",
            "type": null,
            "locator": "span[data-test=\"transaction-receiver-8bFo_NwEf\"]"
          },
          {
            "text": "-$13.00",
            "details": "-$13.00",
            "type": null,
            "locator": "span[data-test=\"transaction-amount-8bFo_NwEf\"]"
          },
          {
            "text": "",
            "details": "",
            "type": null,
            "locator": "button[data-test=\"transaction-like-button-8bFo_NwEf\"] > span:nth-of-type(1)"
          },
          {
            "text": "",
            "details": "",
            "type": null,
            "locator": "button[data-test=\"transaction-like-button-8bFo_NwEf\"] > span:nth-of-type(2)"
          },
          {
            "text": "",
            "details": "",
            "type": null,
            "locator": "legend > span"
          },
          {
            "text": "Devon Becker paid Edgar Johns",
            "details": "Devon Becker paid Edgar Johns",
            "type": null,
            "locator": "p.makeStyles-title-117"
          },
          {
            "text": "Payment-567516",
            "details": "Payment-567516",
            "type": null,
            "locator": "p[data-test=\"transaction-description\"]"
          },
          {
            "text": "Built by",
            "details": "Built by",
            "type": null,
            "locator": "p.MuiTypography-alignCenter"
          }
        ],
        "input": [
          {
            "text": "",
            "details": "Write a comment...",
            "type": "text",
            "locator": "input"
          }
        ],
        "actions": [
          {
            "text": "",
            "locator": "button[data-test=\"sidenav-toggle\"]"
          },
          {
            "text": "",
            "locator": "a.MuiTypography-root"
          },
          {
            "text": " New",
            "locator": "a[data-test=\"nav-top-new-transaction\"]"
          },
          {
            "text": "8",
            "locator": "a[data-test=\"nav-top-notifications-link\"]"
          },
          {
            "text": "Home",
            "locator": "a[data-test=\"sidenav-home\"]"
          },
          {
            "text": "My Account",
            "locator": "a[data-test=\"sidenav-user-settings\"]"
          },
          {
            "text": "Bank Accounts",
            "locator": "a[data-test=\"sidenav-bankaccounts\"]"
          },
          {
            "text": "Notifications",
            "locator": "a[data-test=\"sidenav-notifications\"]"
          },
          {
            "text": "",
            "locator": "button[data-test=\"transaction-like-button-8bFo_NwEf\"]"
          },
          {
            "text": "",
            "locator": "a[target=\"_blank\"]"
          }
        ],
        "iterable": [
          {
            "locator": "ul, ol",
            "iteratorName": "List Iterator",
            "elements": []
          }
        ]
      }
    },
    "/transaction/{transactionId}": {
      "items": {
        "info": [
          {
            "text": "",
            "details": "",
            "type": null,
            "locator": "h1"
          },
          {
            "text": "Devon B",
            "details": "Devon B",
            "type": null,
            "locator": "h6[data-test=\"sidenav-user-full-name\"]"
          },
          {
            "text": "@Jessyca.Kuhic",
            "details": "@Jessyca.Kuhic",
            "type": null,
            "locator": "h6[data-test=\"sidenav-username\"]"
          },
          {
            "text": "$636.69",
            "details": "$636.69",
            "type": null,
            "locator": "h6[data-test=\"sidenav-user-balance\"]"
          },
          {
            "text": "Account Balance",
            "details": "Account Balance",
            "type": null,
            "locator": "div.MuiDrawer-paper > div:nth-of-type(2) > div:nth-of-type(1) > h6:nth-of-type(2)"
          },
          {
            "text": "Transaction Detail",
            "details": "Transaction Detail",
            "type": null,
            "locator": "h2"
          },
          {
            "text": "",
            "details": "",
            "type": null,
            "locator": "button[data-test=\"sidenav-toggle\"] > span:nth-of-type(1)"
          },
          {
            "text": "",
            "details": "",
            "type": null,
            "locator": "button[data-test=\"sidenav-toggle\"] > span:nth-of-type(2)"
          },
          {
            "text": " New",
            "details": "New",
            "type": null,
            "locator": "span.MuiButton-label"
          },
          {
            "text": "",
            "details": "",
            "type": null,
            "locator": "a[data-test=\"nav-top-new-transaction\"] > span:nth-of-type(2)"
          },
          {
            "text": "8",
            "details": "8",
            "type": null,
            "locator": "a[data-test=\"nav-top-notifications-link\"] > span:nth-of-type(1)"
          },
          {
            "text": "8",
            "details": "8",
            "type": null,
            "locator": "span[data-test=\"nav-top-notifications-count\"]"
          },
          {
            "text": "8",
            "details": "8",
            "type": null,
            "locator": "span.MuiBadge-badge"
          },
          {
            "text": "",
            "details": "",
            "type": null,
            "locator": "a[data-test=\"nav-top-notifications-link\"] > span:nth-of-type(2)"
          },
          {
            "text": "Home",
            "details": "Home",
            "type": null,
            "locator": "a[data-test=\"sidenav-home\"] > div:nth-of-type(2) > span"
          },
          {
            "text": "",
            "details": "",
            "type": null,
            "locator": "a[data-test=\"sidenav-home\"] > span"
          },
          {
            "text": "My Account",
            "details": "My Account",
            "type": null,
            "locator": "a[data-test=\"sidenav-user-settings\"] > div:nth-of-type(2) > span"
          },
          {
            "text": "",
            "details": "",
            "type": null,
            "locator": "a[data-test=\"sidenav-user-settings\"] > span"
          },
          {
            "text": "Bank Accounts",
            "details": "Bank Accounts",
            "type": null,
            "locator": "a[data-test=\"sidenav-bankaccounts\"] > div:nth-of-type(2) > span"
          },
          {
            "text": "",
            "details": "",
            "type": null,
            "locator": "a[data-test=\"sidenav-bankaccounts\"] > span"
          },
          {
            "text": "Notifications",
            "details": "Notifications",
            "type": null,
            "locator": "a[data-test=\"sidenav-notifications\"] > div:nth-of-type(2) > span"
          },
          {
            "text": "",
            "details": "",
            "type": null,
            "locator": "a[data-test=\"sidenav-notifications\"] > span"
          },
          {
            "text": "Logout",
            "details": "Logout",
            "type": null,
            "locator": "div[tabindex=\"0\"] > div:nth-of-type(2) > span"
          },
          {
            "text": "",
            "details": "",
            "type": null,
            "locator": "div[tabindex=\"0\"] > span"
          },
          {
            "text": "Devon Becker",
            "details": "Devon Becker",
            "type": null,
            "locator": "span[data-test=\"transaction-sender-E9PfY8ScJ\"]"
          },
          {
            "text": " paid ",
            "details": "paid",
            "type": null,
            "locator": "span[data-test=\"transaction-action-E9PfY8ScJ\"]"
          },
          {
            "text": "Edgar Johns",
            "details": "Edgar Johns",
            "type": null,
            "locator": "span[data-test=\"transaction-receiver-E9PfY8ScJ\"]"
          },
          {
            "text": "-$13.00",
            "details": "-$13.00",
            "type": null,
            "locator": "span[data-test=\"transaction-amount-E9PfY8ScJ\"]"
          },
          {
            "text": "",
            "details": "",
            "type": null,
            "locator": "button[data-test=\"transaction-like-button-E9PfY8ScJ\"] > span:nth-of-type(1)"
          },
          {
            "text": "",
            "details": "",
            "type": null,
            "locator": "button[data-test=\"transaction-like-button-E9PfY8ScJ\"] > span:nth-of-type(2)"
          },
          {
            "text": "",
            "details": "",
            "type": null,
            "locator": "legend > span"
          },
          {
            "text": "Devon Becker paid Edgar Johns",
            "details": "Devon Becker paid Edgar Johns",
            "type": null,
            "locator": "p.makeStyles-title-117"
          },
          {
            "text": "Payment-970537",
            "details": "Payment-970537",
            "type": null,
            "locator": "p[data-test=\"transaction-description\"]"
          },
          {
            "text": "Built by",
            "details": "Built by",
            "type": null,
            "locator": "p.MuiTypography-alignCenter"
          }
        ],
        "input": [
          {
            "text": "",
            "details": "Write a comment...",
            "type": "text",
            "locator": "input"
          }
        ],
        "actions": [
          {
            "text": "",
            "locator": "button[data-test=\"sidenav-toggle\"]"
          },
          {
            "text": "",
            "locator": "a.MuiTypography-root"
          },
          {
            "text": " New",
            "locator": "a[data-test=\"nav-top-new-transaction\"]"
          },
          {
            "text": "8",
            "locator": "a[data-test=\"nav-top-notifications-link\"]"
          },
          {
            "text": "Home",
            "locator": "a[data-test=\"sidenav-home\"]"
          },
          {
            "text": "My Account",
            "locator": "a[data-test=\"sidenav-user-settings\"]"
          },
          {
            "text": "Bank Accounts",
            "locator": "a[data-test=\"sidenav-bankaccounts\"]"
          },
          {
            "text": "Notifications",
            "locator": "a[data-test=\"sidenav-notifications\"]"
          },
          {
            "text": "",
            "locator": "button[data-test=\"transaction-like-button-E9PfY8ScJ\"]"
          },
          {
            "text": "",
            "locator": "a[target=\"_blank\"]"
          }
        ],
        "iterable": [
          {
            "locator": "ul, ol",
            "iteratorName": "List Iterator",
            "elements": []
          }
        ]
      }
    },
    "/bankaccounts": {
      "items": {
        "info": [
          {
            "text": "",
            "details": "",
            "type": null,
            "locator": "h1"
          },
          {
            "text": "Devon B",
            "details": "Devon B",
            "type": null,
            "locator": "h6[data-test=\"sidenav-user-full-name\"]"
          },
          {
            "text": "@Jessyca.Kuhic",
            "details": "@Jessyca.Kuhic",
            "type": null,
            "locator": "h6[data-test=\"sidenav-username\"]"
          },
          {
            "text": "$753.69",
            "details": "$753.69",
            "type": null,
            "locator": "h6[data-test=\"sidenav-user-balance\"]"
          },
          {
            "text": "Account Balance",
            "details": "Account Balance",
            "type": null,
            "locator": "div.MuiDrawer-paper > div:nth-of-type(2) > div:nth-of-type(1) > h6:nth-of-type(2)"
          },
          {
            "text": "Bank Accounts",
            "details": "Bank Accounts",
            "type": null,
            "locator": "h2"
          },
          {
            "text": "",
            "details": "",
            "type": null,
            "locator": "button[data-test=\"sidenav-toggle\"] > span:nth-of-type(1)"
          },
          {
            "text": "",
            "details": "",
            "type": null,
            "locator": "button[data-test=\"sidenav-toggle\"] > span:nth-of-type(2)"
          },
          {
            "text": " New",
            "details": "New",
            "type": null,
            "locator": "a[data-test=\"nav-top-new-transaction\"] > span:nth-of-type(1)"
          },
          {
            "text": "",
            "details": "",
            "type": null,
            "locator": "a[data-test=\"nav-top-new-transaction\"] > span:nth-of-type(2)"
          },
          {
            "text": "8",
            "details": "8",
            "type": null,
            "locator": "a[data-test=\"nav-top-notifications-link\"] > span:nth-of-type(1)"
          },
          {
            "text": "8",
            "details": "8",
            "type": null,
            "locator": "span[data-test=\"nav-top-notifications-count\"]"
          },
          {
            "text": "8",
            "details": "8",
            "type": null,
            "locator": "span.MuiBadge-badge"
          },
          {
            "text": "",
            "details": "",
            "type": null,
            "locator": "a[data-test=\"nav-top-notifications-link\"] > span:nth-of-type(2)"
          },
          {
            "text": "Home",
            "details": "Home",
            "type": null,
            "locator": "a[data-test=\"sidenav-home\"] > div:nth-of-type(2) > span"
          },
          {
            "text": "",
            "details": "",
            "type": null,
            "locator": "a[data-test=\"sidenav-home\"] > span"
          },
          {
            "text": "My Account",
            "details": "My Account",
            "type": null,
            "locator": "a[data-test=\"sidenav-user-settings\"] > div:nth-of-type(2) > span"
          },
          {
            "text": "",
            "details": "",
            "type": null,
            "locator": "a[data-test=\"sidenav-user-settings\"] > span"
          },
          {
            "text": "Bank Accounts",
            "details": "Bank Accounts",
            "type": null,
            "locator": "a[data-test=\"sidenav-bankaccounts\"] > div:nth-of-type(2) > span"
          },
          {
            "text": "",
            "details": "",
            "type": null,
            "locator": "a[data-test=\"sidenav-bankaccounts\"] > span"
          },
          {
            "text": "Notifications",
            "details": "Notifications",
            "type": null,
            "locator": "a[data-test=\"sidenav-notifications\"] > div:nth-of-type(2) > span"
          },
          {
            "text": "",
            "details": "",
            "type": null,
            "locator": "a[data-test=\"sidenav-notifications\"] > span"
          },
          {
            "text": "Logout",
            "details": "Logout",
            "type": null,
            "locator": "div[tabindex=\"0\"] > div:nth-of-type(2) > span"
          },
          {
            "text": "",
            "details": "",
            "type": null,
            "locator": "div[tabindex=\"0\"] > span"
          },
          {
            "text": "Create",
            "details": "Create",
            "type": null,
            "locator": "a[data-test=\"bankaccount-new\"] > span:nth-of-type(1)"
          },
          {
            "text": "",
            "details": "",
            "type": null,
            "locator": "a[data-test=\"bankaccount-new\"] > span:nth-of-type(2)"
          },
          {
            "text": "Delete",
            "details": "Delete",
            "type": null,
            "locator": "li[data-test=\"bankaccount-list-item-KtPcRvTYDCm\"] > div > div:nth-of-type(2) > button > span:nth-of-type(1)"
          },
          {
            "text": "",
            "details": "",
            "type": null,
            "locator": "li[data-test=\"bankaccount-list-item-KtPcRvTYDCm\"] > div > div:nth-of-type(2) > button > span:nth-of-type(2)"
          },
          {
            "text": "Delete",
            "details": "Delete",
            "type": null,
            "locator": "li[data-test=\"bankaccount-list-item-A2dpILrDn\"] > div > div:nth-of-type(2) > button > span:nth-of-type(1)"
          },
          {
            "text": "",
            "details": "",
            "type": null,
            "locator": "li[data-test=\"bankaccount-list-item-A2dpILrDn\"] > div > div:nth-of-type(2) > button > span:nth-of-type(2)"
          },
          {
            "text": "Delete",
            "details": "Delete",
            "type": null,
            "locator": "li[data-test=\"bankaccount-list-item-pjY1ZJsdn\"] > div > div:nth-of-type(2) > button > span:nth-of-type(1)"
          },
          {
            "text": "",
            "details": "",
            "type": null,
            "locator": "li[data-test=\"bankaccount-list-item-pjY1ZJsdn\"] > div > div:nth-of-type(2) > button > span:nth-of-type(2)"
          },
          {
            "text": "Delete",
            "details": "Delete",
            "type": null,
            "locator": "li[data-test=\"bankaccount-list-item-dIlMuAtEk\"] > div > div:nth-of-type(2) > button > span:nth-of-type(1)"
          },
          {
            "text": "",
            "details": "",
            "type": null,
            "locator": "li[data-test=\"bankaccount-list-item-dIlMuAtEk\"] > div > div:nth-of-type(2) > button > span:nth-of-type(2)"
          },
          {
            "text": "Dickinson - Goodwin Bank ",
            "details": "Dickinson - Goodwin Bank",
            "type": null,
            "locator": "li[data-test=\"bankaccount-list-item-KtPcRvTYDCm\"] > div > div:nth-of-type(1) > p"
          },
          {
            "text": "Revolut-Loop-717707 (Deleted)",
            "details": "Revolut-Loop-717707 (Deleted)",
            "type": null,
            "locator": "li[data-test=\"bankaccount-list-item-oiIFZ3sWV\"] > div > div > p"
          },
          {
            "text": "Revolut-Loop-762771 (Deleted)",
            "details": "Revolut-Loop-762771 (Deleted)",
            "type": null,
            "locator": "li[data-test=\"bankaccount-list-item-mKy4Vil-e\"] > div > div > p"
          },
          {
            "text": "Revolut-Loop-122850 (Deleted)",
            "details": "Revolut-Loop-122850 (Deleted)",
            "type": null,
            "locator": "li[data-test=\"bankaccount-list-item-HpYKg1GkN\"] > div > div > p"
          },
          {
            "text": "Revolut-Loop-40231 (Deleted)",
            "details": "Revolut-Loop-40231 (Deleted)",
            "type": null,
            "locator": "li[data-test=\"bankaccount-list-item-iNLVvVnvk\"] > div > div > p"
          },
          {
            "text": "Revolut-Loop-725117 (Deleted)",
            "details": "Revolut-Loop-725117 (Deleted)",
            "type": null,
            "locator": "li[data-test=\"bankaccount-list-item-JGAYRlqQ6\"] > div > div > p"
          },
          {
            "text": "Revolut-Loop-664548 (Deleted)",
            "details": "Revolut-Loop-664548 (Deleted)",
            "type": null,
            "locator": "li[data-test=\"bankaccount-list-item-SouHruaMR\"] > div > div > p"
          },
          {
            "text": "Revolut-Loop-845803 (Deleted)",
            "details": "Revolut-Loop-845803 (Deleted)",
            "type": null,
            "locator": "li[data-test=\"bankaccount-list-item-EXhQfLazU\"] > div > div > p"
          },
          {
            "text": "Revolut-Loop-972411 (Deleted)",
            "details": "Revolut-Loop-972411 (Deleted)",
            "type": null,
            "locator": "li[data-test=\"bankaccount-list-item-HI-9eZWtF\"] > div > div > p"
          },
          {
            "text": "Revolut-Loop-450223 ",
            "details": "Revolut-Loop-450223",
            "type": null,
            "locator": "li[data-test=\"bankaccount-list-item-A2dpILrDn\"] > div > div:nth-of-type(1) > p"
          },
          {
            "text": "Revolut-Loop-369686 ",
            "details": "Revolut-Loop-369686",
            "type": null,
            "locator": "li[data-test=\"bankaccount-list-item-pjY1ZJsdn\"] > div > div:nth-of-type(1) > p"
          },
          {
            "text": "Revolut-Loop-626726 ",
            "details": "Revolut-Loop-626726",
            "type": null,
            "locator": "li[data-test=\"bankaccount-list-item-dIlMuAtEk\"] > div > div:nth-of-type(1) > p"
          },
          {
            "text": "Built by",
            "details": "Built by",
            "type": null,
            "locator": "p.MuiTypography-body2"
          }
        ],
        "input": [],
        "actions": [
          {
            "text": "",
            "locator": "button[data-test=\"sidenav-toggle\"]"
          },
          {
            "text": "",
            "locator": "a.MuiTypography-root"
          },
          {
            "text": " New",
            "locator": "a[data-test=\"nav-top-new-transaction\"]"
          },
          {
            "text": "8",
            "locator": "a[data-test=\"nav-top-notifications-link\"]"
          },
          {
            "text": "Home",
            "locator": "a[data-test=\"sidenav-home\"]"
          },
          {
            "text": "My Account",
            "locator": "a[data-test=\"sidenav-user-settings\"]"
          },
          {
            "text": "Bank Accounts",
            "locator": "a[data-test=\"sidenav-bankaccounts\"]"
          },
          {
            "text": "Notifications",
            "locator": "a[data-test=\"sidenav-notifications\"]"
          },
          {
            "text": "Create",
            "locator": "a[data-test=\"bankaccount-new\"]"
          },
          {
            "text": "Delete",
            "locator": "li[data-test=\"bankaccount-list-item-KtPcRvTYDCm\"] > div > div:nth-of-type(2) > button"
          },
          {
            "text": "Delete",
            "locator": "li[data-test=\"bankaccount-list-item-A2dpILrDn\"] > div > div:nth-of-type(2) > button"
          },
          {
            "text": "Delete",
            "locator": "li[data-test=\"bankaccount-list-item-pjY1ZJsdn\"] > div > div:nth-of-type(2) > button"
          },
          {
            "text": "Delete",
            "locator": "li[data-test=\"bankaccount-list-item-dIlMuAtEk\"] > div > div:nth-of-type(2) > button"
          },
          {
            "text": "",
            "locator": "a[target=\"_blank\"]"
          }
        ],
        "iterable": [
          {
            "locator": "ul, ol",
            "iteratorName": "List Iterator",
            "elements": []
          }
        ]
      }
    },
    "/bankaccounts/new": {
      "items": {
        "info": [
          {
            "text": "",
            "details": "",
            "type": null,
            "locator": "h1"
          },
          {
            "text": "Devon B",
            "details": "Devon B",
            "type": null,
            "locator": "h6[data-test=\"sidenav-user-full-name\"]"
          },
          {
            "text": "@Jessyca.Kuhic",
            "details": "@Jessyca.Kuhic",
            "type": null,
            "locator": "h6[data-test=\"sidenav-username\"]"
          },
          {
            "text": "$636.69",
            "details": "$636.69",
            "type": null,
            "locator": "h6[data-test=\"sidenav-user-balance\"]"
          },
          {
            "text": "Account Balance",
            "details": "Account Balance",
            "type": null,
            "locator": "div.MuiDrawer-paper > div:nth-of-type(2) > div:nth-of-type(1) > h6:nth-of-type(2)"
          },
          {
            "text": "Create Bank Account",
            "details": "Create Bank Account",
            "type": null,
            "locator": "h2"
          },
          {
            "text": "",
            "details": "",
            "type": null,
            "locator": "button[type=\"button\"] > span:nth-of-type(1)"
          },
          {
            "text": "",
            "details": "",
            "type": null,
            "locator": "button[type=\"button\"] > span:nth-of-type(2)"
          },
          {
            "text": " New",
            "details": "New",
            "type": null,
            "locator": "a[data-test=\"nav-top-new-transaction\"] > span:nth-of-type(1)"
          },
          {
            "text": "",
            "details": "",
            "type": null,
            "locator": "a[data-test=\"nav-top-new-transaction\"] > span:nth-of-type(2)"
          },
          {
            "text": "8",
            "details": "8",
            "type": null,
            "locator": "a[data-test=\"nav-top-notifications-link\"] > span:nth-of-type(1)"
          },
          {
            "text": "8",
            "details": "8",
            "type": null,
            "locator": "span[data-test=\"nav-top-notifications-count\"]"
          },
          {
            "text": "8",
            "details": "8",
            "type": null,
            "locator": "span.MuiBadge-badge"
          },
          {
            "text": "",
            "details": "",
            "type": null,
            "locator": "a[data-test=\"nav-top-notifications-link\"] > span:nth-of-type(2)"
          },
          {
            "text": "Home",
            "details": "Home",
            "type": null,
            "locator": "a[data-test=\"sidenav-home\"] > div:nth-of-type(2) > span"
          },
          {
            "text": "",
            "details": "",
            "type": null,
            "locator": "a[data-test=\"sidenav-home\"] > span"
          },
          {
            "text": "My Account",
            "details": "My Account",
            "type": null,
            "locator": "a[data-test=\"sidenav-user-settings\"] > div:nth-of-type(2) > span"
          },
          {
            "text": "",
            "details": "",
            "type": null,
            "locator": "a[data-test=\"sidenav-user-settings\"] > span"
          },
          {
            "text": "Bank Accounts",
            "details": "Bank Accounts",
            "type": null,
            "locator": "a[data-test=\"sidenav-bankaccounts\"] > div:nth-of-type(2) > span"
          },
          {
            "text": "",
            "details": "",
            "type": null,
            "locator": "a[data-test=\"sidenav-bankaccounts\"] > span"
          },
          {
            "text": "Notifications",
            "details": "Notifications",
            "type": null,
            "locator": "a[data-test=\"sidenav-notifications\"] > div:nth-of-type(2) > span"
          },
          {
            "text": "",
            "details": "",
            "type": null,
            "locator": "a[data-test=\"sidenav-notifications\"] > span"
          },
          {
            "text": "Logout",
            "details": "Logout",
            "type": null,
            "locator": "div[tabindex=\"0\"] > div:nth-of-type(2) > span"
          },
          {
            "text": "",
            "details": "",
            "type": null,
            "locator": "div[tabindex=\"0\"] > span"
          },
          {
            "text": "",
            "details": "",
            "type": null,
            "locator": "div[data-test=\"bankaccount-bankName-input\"] > div > fieldset > legend > span"
          },
          {
            "text": "",
            "details": "",
            "type": null,
            "locator": "div[data-test=\"bankaccount-routingNumber-input\"] > div > fieldset > legend > span"
          },
          {
            "text": "",
            "details": "",
            "type": null,
            "locator": "div[data-test=\"bankaccount-accountNumber-input\"] > div > fieldset > legend > span"
          },
          {
            "text": "Save",
            "details": "Save",
            "type": null,
            "locator": "button[type=\"submit\"] > span:nth-of-type(1)"
          },
          {
            "text": "",
            "details": "",
            "type": null,
            "locator": "button[type=\"submit\"] > span:nth-of-type(2)"
          },
          {
            "text": "Built by",
            "details": "Built by",
            "type": null,
            "locator": "p"
          }
        ],
        "input": [
          {
            "text": "",
            "details": "Bank Name",
            "type": "text",
            "locator": "input#bankaccount-bankName-input"
          },
          {
            "text": "",
            "details": "Routing Number",
            "type": "text",
            "locator": "input#bankaccount-routingNumber-input"
          },
          {
            "text": "",
            "details": "Account Number",
            "type": "text",
            "locator": "input#bankaccount-accountNumber-input"
          }
        ],
        "actions": [
          {
            "text": "",
            "locator": "button[type=\"button\"]"
          },
          {
            "text": "",
            "locator": "a.MuiTypography-root"
          },
          {
            "text": " New",
            "locator": "a[data-test=\"nav-top-new-transaction\"]"
          },
          {
            "text": "8",
            "locator": "a[data-test=\"nav-top-notifications-link\"]"
          },
          {
            "text": "Home",
            "locator": "a[data-test=\"sidenav-home\"]"
          },
          {
            "text": "My Account",
            "locator": "a[data-test=\"sidenav-user-settings\"]"
          },
          {
            "text": "Bank Accounts",
            "locator": "a[data-test=\"sidenav-bankaccounts\"]"
          },
          {
            "text": "Notifications",
            "locator": "a[data-test=\"sidenav-notifications\"]"
          },
          {
            "text": "Save",
            "locator": "button[type=\"submit\"]"
          },
          {
            "text": "",
            "locator": "a[target=\"_blank\"]"
          }
        ],
        "iterable": [
          {
            "locator": "ul, ol",
            "iteratorName": "List Iterator",
            "elements": []
          }
        ]
      }
    }
  }
}